<?xml version="1.0"?>
<!-- Generated by SimpleXMLDoc helper.  Executed Thu Aug 4 23:03:01 UTC+0200 2011 by Stefan -->
<xsi_file type="AddonInfo" xsi_version="10.1.62.0" syntax_version="1.0">
	<Categories></Categories>
	<PlatForms></PlatForms>
	<Title></Title>
	<AuthorName>Stefan Kubicek; Eugen Sares</AuthorName>
	<AuthorEMail>stefan@keyvis.at; eugen@keyvis.at</AuthorEMail>
	<Company>keyvis digital imagery</Company>
	<URL>http://www.keyvis.at/?page_id=68</URL>
	<Language></Language>
	<Summary></Summary>
	<Usage></Usage>
</xsi_file>
